jyk_logging-1.0.3-py3.8-nspkg.pth
jyk/logging/__init__.py
jyk/logging/colors.py
jyk/logging/core.py
jyk/logging/exceptions.py
jyk/logging/formatter.py
jyk/logging/task.py
jyk/logging/test.py
jyk_logging-1.0.3.dist-info/LICENSE
jyk_logging-1.0.3.dist-info/METADATA
jyk_logging-1.0.3.dist-info/WHEEL
jyk_logging-1.0.3.dist-info/namespace_packages.txt
jyk_logging-1.0.3.dist-info/top_level.txt
jyk_logging-1.0.3.dist-info/RECORD
