Metadata-Version: 2.1
Name: jyk-logging
Version: 1.0.3
Summary: jyk logging utils package
Home-page: https://git.kongkongss.com/jyker/jyk-logging
Author: Kongkong Jiang
Author-email: jyk.kongkong@gmail.com
License: MIT
Keywords: jyk logging
Platform: UNKNOWN
Requires-Python: >=3.7.1
Requires-Dist: jyk-timer
